README.rst
aoc_to_markdown.py
setup.py
aoc_to_markdown.egg-info/PKG-INFO
aoc_to_markdown.egg-info/SOURCES.txt
aoc_to_markdown.egg-info/dependency_links.txt
aoc_to_markdown.egg-info/entry_points.txt
aoc_to_markdown.egg-info/requires.txt
aoc_to_markdown.egg-info/top_level.txt